quasarr/__init__.py
quasarr/api/__init__.py
quasarr/api/arr/__init__.py
quasarr/api/captcha/__init__.py
quasarr/api/config/__init__.py
quasarr/api/sponsors_helper/__init__.py
quasarr/api/statistics/__init__.py
quasarr/downloads/__init__.py
quasarr/downloads/linkcrypters/__init__.py
quasarr/downloads/linkcrypters/al.py
quasarr/downloads/linkcrypters/filecrypt.py
quasarr/downloads/linkcrypters/hide.py
quasarr/downloads/packages/__init__.py
quasarr/downloads/sources/__init__.py
quasarr/downloads/sources/al.py
quasarr/downloads/sources/by.py
quasarr/downloads/sources/dd.py
quasarr/downloads/sources/dj.py
quasarr/downloads/sources/dl.py
quasarr/downloads/sources/dt.py
quasarr/downloads/sources/dw.py
quasarr/downloads/sources/he.py
quasarr/downloads/sources/mb.py
quasarr/downloads/sources/nk.py
quasarr/downloads/sources/nx.py
quasarr/downloads/sources/sf.py
quasarr/downloads/sources/sj.py
quasarr/downloads/sources/sl.py
quasarr/downloads/sources/wd.py
quasarr/downloads/sources/wx.py
quasarr/providers/__init__.py
quasarr/providers/cloudflare.py
quasarr/providers/html_images.py
quasarr/providers/html_templates.py
quasarr/providers/imdb_metadata.py
quasarr/providers/log.py
quasarr/providers/myjd_api.py
quasarr/providers/notifications.py
quasarr/providers/obfuscated.py
quasarr/providers/shared_state.py
quasarr/providers/statistics.py
quasarr/providers/utils.py
quasarr/providers/version.py
quasarr/providers/web_server.py
quasarr/providers/sessions/__init__.py
quasarr/providers/sessions/al.py
quasarr/providers/sessions/dd.py
quasarr/providers/sessions/dl.py
quasarr/providers/sessions/nx.py
quasarr/search/__init__.py
quasarr/search/sources/__init__.py
quasarr/search/sources/al.py
quasarr/search/sources/by.py
quasarr/search/sources/dd.py
quasarr/search/sources/dj.py
quasarr/search/sources/dl.py
quasarr/search/sources/dt.py
quasarr/search/sources/dw.py
quasarr/search/sources/fx.py
quasarr/search/sources/he.py
quasarr/search/sources/mb.py
quasarr/search/sources/nk.py
quasarr-1.29.0.dist-info/licenses/LICENSE
quasarr-1.29.0.dist-info/METADATA
quasarr-1.29.0.dist-info/WHEEL
quasarr-1.29.0.dist-info/entry_points.txt
quasarr-1.29.0.dist-info/top_level.txt
quasarr-1.29.0.dist-info/RECORD
